pythena/Athena.py
pythena/Exceptions.py
pythena/Utils.py
pythena/__init__.py
ztech_pythena-0.0.3.dist-info/LICENSE
ztech_pythena-0.0.3.dist-info/METADATA
ztech_pythena-0.0.3.dist-info/WHEEL
ztech_pythena-0.0.3.dist-info/top_level.txt
ztech_pythena-0.0.3.dist-info/RECORD
