Metadata-Version: 2.1
Name: ztech-pythena
Version: 0.0.3
Summary: A simple athena wrapper (forked from chris.pruitt) leveraging boto3 to execute queries and return results while only requiring a database and a query string.
Home-page: https://github.com/ztech-company/pythena
Author: felipe.tancredo
Author-email: felipetancredo@gmail.com
License: Mozilla Public License Version 2.0
Platform: UNKNOWN
Requires-Dist: pandas (>=0.22.0)
Requires-Dist: boto3 (>=1.9.90)
Requires-Dist: botocore (>=1.12.90)
Requires-Dist: retrying (>=1.3.3)
